fritz_advanced_thermostat/__init__.py
fritz_advanced_thermostat/errors.py
fritz_advanced_thermostat/fritz_advanced_thermostat.py
fritz_advanced_thermostat-0.2.5.dist-info/LICENSE
fritz_advanced_thermostat-0.2.5.dist-info/METADATA
fritz_advanced_thermostat-0.2.5.dist-info/WHEEL
fritz_advanced_thermostat-0.2.5.dist-info/top_level.txt
fritz_advanced_thermostat-0.2.5.dist-info/RECORD
