Metadata-Version: 2.1
Name: fritz-advanced-thermostat
Version: 0.2.5
Summary: A library for setting FRITZ!DECT thermostat values (e.g. offset, holidays, timer), that can't be set via AHA requests.
Home-page: https://github.com/mietzen/python-fritz-advanced-thermostat
Author: Nils Stein
Author-email: github.nstein@mailbox.org
License: MIT
Keywords: fritzbox smarthome avm thermostat
Classifier: Development Status :: 4 - Beta
Classifier: License :: OSI Approved :: MIT License
Classifier: Programming Language :: Python :: 3.9
Classifier: Programming Language :: Python :: 3.10
Classifier: Programming Language :: Python :: 3.11
Classifier: Operating System :: OS Independent
License-File: LICENSE
Requires-Dist: fritzconnection >=1.12.2
Requires-Dist: pyfritzhome >=0.6.8
Requires-Dist: requests >=2.31.0
Requires-Dist: selenium ==4.10.0
Requires-Dist: packaging >=23.1
